{
  "portfolio": "the-american-west",
  "order": 22,
  "slug": "sea-slot-pacific-coast",
  "title": "Sea Slot",
  "state": "California",
  "year": 2010,
  "place": "Pacific Coast",
  "location": "Davenport",
  "field-notes": "This is a field note.",
  "print-type": "Pigment Ink",
  "edition": "25",
  "edition-type": "Limited",
  "image": "sea-slot-pacific-coast.jpg",
  "thumb": "sea-slot-pacific-coast.jpg",
  "image-home": "sea-slot-pacific-coast-home.jpg",
  "image-biz": "sea-slot-pacific-coast-biz.jpg",
  "width": 1100,
  "height": 1600
}